localbus/__init__.py
localbus/bus.py
localbus/localbus.py
localbus-0.0.4.dist-info/LICENSE
localbus-0.0.4.dist-info/METADATA
localbus-0.0.4.dist-info/WHEEL
localbus-0.0.4.dist-info/top_level.txt
localbus-0.0.4.dist-info/RECORD
